<VIEW>
   <MASKDEF key="TeachView.mask.LinearChanger" textfile="userTx" permissiondef="userMenuPermission">  
       <GROUP key="LinearChanger.label.group1" col="1" row="1" columns="40" rows="40" cspan="40" rspan="40" halign="stretch"  valign="stretch"> 
       
       <GROUP  col="1" row="1" columns="40" rows="12" cspan="40" rspan="12" halign="stretch"  valign="stretch">
      	   	  	
   	  		
	  <LABEL key="LinearChanger.label.lab_2" 
	         col="2" 
	         row="2"/>	    
	          
	  <NUMFIELD var="PCU1.SV_PCU2PHG.tLinearUnit[1].sOut.o_rPosition" 
	            vartype="SV"
                    enabled="false" 
                    col="10" 
                    row="2" 
                    cspan="6" 
                    halign="stretch" 
                    rspan="3" 
                    valign="stretch"/>

	  <LABEL key="LinearChanger.label.lab_3" 
	         col="2" 
	         row="6"/>	  
	         
	  <NUMFIELD var="PCU1.SV_PCU2PHG.tLinearUnit[1].sOut.o_iValvePosition" 
	            vartype="SV"
                    enabled="false" 
                    col="10" 
                    row="6" 
                    cspan="6" 
                    halign="stretch" 
                    rspan="3" 
                    valign="stretch"/>
                    
        </GROUP>	
        
        <GROUP  col="1" row="13" columns="40" rows="14" cspan="40" rspan="14" halign="stretch"  valign="stretch">   
            

	  <CHECKBOX key="LinearChanger.chkbox.setrefmode"
	            vartype="SV" 
	            col="2" 
	            row="2" 
	            halign="left" 
	            enablevar="PCU1.SV_PCU2PHG.tLinearUnit[1].sOut.o_mEnableReferenceMode" 
	            enablevartype="SV" 
	            var="PCU1.SV_PCU2PHG.tLinearUnit[1].sIn.i_mSetReferenceMode" />
	            
	  <LABEL key="LinearChanger.label.lab_1" 
	         col="5" 
	         row="2" />
	         
	  <CHECKBOX vartype="SV" col="23" row="2" halign="left" enabled="false" var="PCU1.SV_PCU2PHG.tLinearUnit[1].sOut.o_mMasterModeOk" />
   	  <LABEL key="LinearChanger.label.ModeOk" col="26" row="2" halign="left" />        
   	  
   	  <CHECKBOX vartype="SV" col="23" row="6" halign="left" enabled="false" var="PCU1.SV_PCU2PHG.tLinearUnit[1].sOut.o_mMasterPneumaticOk" />
   	  <LABEL key="LinearChanger.label.PneumaticOk" col="26" row="6" halign="left" />        
   	  
   	  <CHECKBOX vartype="SV" col="23" row="10" halign="left" enabled="false" var="PCU1.SV_PCU2PHG.tLinearUnit[1].sOut.o_mMasterOrderOk" />
   	  <LABEL key="LinearChanger.label.AlanOk" col="26" row="10" halign="left" />
	         
	 </GROUP> 
	 
	 <GROUP  col="1" row="27" columns="40" rows="14" cspan="40" rspan="14" halign="stretch"  valign="stretch">         
                    
   	  <BUTTON var="PCU1.SV_PCU2PHG.tLinearUnit[1].sIn.i_mSetReference" 
   	          vartype="SV" 
   	          enablevar="PCU1.SV_PCU2PHG.tLinearUnit[1].sOut.o_mEnableReferenceButton" 
   	          enablevartype="SV" 
                  key="LinearChanger.button.lab_1" 
   	          col="2" 
   	          row="2" 
   	          cspan="10" 
   	          halign="stretch" 
   	          rspan="5" 
   	          valign="stretch"/>
   	          
   	  
   	  <CHECKBOX vartype="SV" col="23" row="2" halign="left" enabled="false" var="PCU1.SV_PCU2PHG.tLinearUnit[1].sOut.o_mMasterUndockedOk" />
   	  <LABEL key="LinearChanger.label.UndockedOk" col="26" row="2" halign="left" />        
   	  
   	  <CHECKBOX vartype="SV" col="23" row="6" halign="left" enabled="false" var="PCU1.SV_PCU2PHG.tLinearUnit[1].sOut.o_mMasterSPC200Off" />
   	  <LABEL key="LinearChanger.label.SPC200Off" col="26" row="6" halign="left" />        	
   	  
   	     
   	  
         </GROUP>
                    	  
	  	  
       </GROUP>		  
   </MASKDEF>
</VIEW>
